annealing_ab/__init__.py
annealing_ab/algo/__init__.py
annealing_ab/algo/annealing_ab.py
annealing_ab/algo/strat_annealing_ab.py
annealing_ab/analysis/__init__.py
annealing_ab/analysis/charts.py
annealing_ab/analysis/results.py
annealing_ab/examples/example.ipynb
annealing_ab/loss/__init__.py
annealing_ab/loss/losses.py
annealing_ab/optimize/__init__.py
annealing_ab/optimize/optimizer_group.py
annealing_ab/stratify/__init__.py
annealing_ab/stratify/stratify_group.py
annealing_ab-0.0.7.dist-info/licenses/LICENSE
annealing_ab-0.0.7.dist-info/WHEEL
annealing_ab-0.0.7.dist-info/METADATA
annealing_ab-0.0.7.dist-info/RECORD
