Metadata-Version: 2.4
Name: annealing_ab
Version: 0.0.7
Summary: selection of groups for AB tests
Author: Nikolai
Requires-Python: >=3.8
Classifier: Programming Language :: Python :: 3
Classifier: License :: OSI Approved :: MIT License
License-File: LICENSE
Requires-Dist: numpy>=1.24
Requires-Dist: pandas>=2.0
Requires-Dist: seaborn
Requires-Dist: scipy
Requires-Dist: tqdm
Requires-Dist: ruff>=0.5 ; extra == "dev"
Requires-Dist: mkdocs ; extra == "dev"
Requires-Dist: ipython ; extra == "dev"
Requires-Dist: jupyterlab ; extra == "dev"
Requires-Dist: notebook ; extra == "dev"
Requires-Dist: tqdm ; extra == "dev"
Requires-Dist: typer ; extra == "dev"
Requires-Dist: loguru ; extra == "dev"
Requires-Dist: python-dotenv ; extra == "dev"
Requires-Dist: matplotlib ; extra == "dev"
Requires-Dist: scikit-learn ; extra == "dev"
Requires-Dist: seaborn ; extra == "dev"
Requires-Dist: scipy ; extra == "dev"
Requires-Dist: pytest>=7.0 ; extra == "test"
Requires-Dist: pytest-cov>=4.0 ; extra == "test"
Provides-Extra: dev
Provides-Extra: test
